[
  {
    "activityId": 23311998148,
    "activityName": "浦东新区 - 6/13 长距离26km 自控",
    "startTimeLocal": "2026-06-20 08:24:20",
    "startTimeGMT": "2026-06-20 00:24:20",
    "activityType": {
      "typeId": 1,
      "typeKey": "running",
      "parentTypeId": 17,
      "isHidden": false,
      "restricted": false,
      "trimmable": true
    },
    "eventType": {
      "typeId": 9,
      "typeKey": "uncategorized",
      "sortOrder": 10
    },
    "distance": 26008.55078125,
    "duration": 7288.06494140625,
    "elapsedDuration": 8173.841796875,
    "movingDuration": 7279.897979736328,
    "elevationGain": 19.0,
    "elevationLoss": 15.0,
    "averageSpeed": 3.569000005722046,
    "maxSpeed": 4.301000118255615,
    "startLatitude": 31.115752402693033,
    "startLongitude": 121.75630884245038,
    "hasPolyline": true,
    "hasImages": false,
    "ownerId": 94347924,
    "ownerDisplayName": "d8733a73-9d84-4e2b-b100-f54d94291ef5",
    "ownerFullName": "Liuwei",
    "ownerProfileImageUrlSmall": "https://s3.amazonaws.com/garmin-connect-prod/profile_images/87a50364-af13-44c7-8613-ae5b958eef41-94347924.png",
    "ownerProfileImageUrlMedium": "https://s3.amazonaws.com/garmin-connect-prod/profile_images/ea315b38-d30d-481c-b69d-9a291c7ddc2c-94347924.png",
    "ownerProfileImageUrlLarge": "https://s3.amazonaws.com/garmin-connect-prod/profile_images/f0afed8c-b1d9-41cf-a1fe-9ac5fd718d5f-94347924.png",
    "calories": 1396.0,
    "bmrCalories": 144.0,
    "averageHR": 146.0,
    "maxHR": 159.0,
    "averageRunningCadenceInStepsPerMinute": 192.046875,
    "maxRunningCadenceInStepsPerMinute": 199.0,
    "steps": 23234,
    "userRoles": [
      "SCOPE_GOLF_API_READ",
      "SCOPE_DI_OAUTH_2_DEVICE_REVOCATION_WRITE",
      "SCOPE_DI_OAUTH_2_CREATE_DI_USER",
      "SCOPE_ATP_READ",
      "SCOPE_DIVE_API_WRITE",
      "SCOPE_COMMUNITY_COURSE_ADMIN_READ",
      "SCOPE_DIVE_API_READ",
      "SCOPE_DT_ACTIVE_INTELLIGENCE_READ",
      "SCOPE_DI_OAUTH_2_CLIENT_READ",
      "SCOPE_CONNECT_WRITE",
      "SCOPE_COMMUNITY_COURSE_WRITE",
      "SCOPE_CONNECT_MCT_DAILY_LOG_READ",
      "SCOPE_CONNECT_API_CREATE_UPDATE_USER",
      "SCOPE_MESSAGE_GENERATION_READ",
      "SCOPE_DI_OAUTH_2_CLIENT_REVOCATION_ADMIN",
      "SCOPE_CONNECT_WEB_TEMPLATE_RENDER",
      "SCOPE_ACTIVITY_DETECTION_READ",
      "SCOPE_OMT_SUBSCRIPTION_ADMIN_READ",
      "SCOPE_DI_OAUTH_2_MANAGED_STATUS_ADMIN_WRITE",
      "SCOPE_CONNECT_NON_SOCIAL_SHARED_READ",
      "SCOPE_CONNECT_READ",
      "SCOPE_DI_OAUTH_2_PRERELEASE_PERMISSIONS_ADMIN_WRITE",
      "SCOPE_DI_OAUTH_2_TOKEN_ADMIN",
      "SCOPE_ATP_WRITE",
      "ROLE_CONNECTUSER",
      "ROLE_FITNESS_USER",
      "ROLE_WELLNESS_USER",
      "ROLE_OUTDOOR_USER",
      "ROLE_GARMIN_USER"
    ],
    "privacy": {
      "typeId": 2,
      "typeKey": "private"
    },
    "userPro": false,
    "hasVideo": false,
    "timeZoneId": 135,
    "beginTimestamp": 1781915060000,
    "sportTypeId": 1,
    "avgPower": 267.0,
    "maxPower": 337.0,
    "aerobicTrainingEffect": 4.199999809265137,
    "anaerobicTrainingEffect": 0.0,
    "normPower": 268.0,
    "avgVerticalOscillation": 8.01999969482422,
    "avgGroundContactTime": 215.3000030517578,
    "avgStrideLength": 110.95,
    "vO2MaxValue": 64.0,
    "avgVerticalRatio": 7.230000019073486,
    "workoutId": 1591848772,
    "deviceId": 3478486124,
    "minElevation": -1.600000023841858,
    "maxElevation": 7.0,
    "avgElevation": 1.933150385147621,
    "maxDoubleCadence": 199.0,
    "summarizedDiveInfo": {
      "summarizedDiveGases": []
    },
    "maxVerticalSpeed": 0.40000009536743164,
    "manufacturer": "GARMIN",
    "locationName": "浦东新区",
    "lapCount": 27,
    "endLatitude": 31.11528318375349,
    "endLongitude": 121.75571481697261,
    "waterEstimated": 2024.0,
    "trainingEffectLabel": "AEROBIC_BASE",
    "activityTrainingLoad": 206.7488555908203,
    "minActivityLapDuration": 1.8799999952316284,
    "aerobicTrainingEffectMessage": "HIGHLY_IMPROVING_AEROBIC_ENDURANCE_10",
    "anaerobicTrainingEffectMessage": "NO_ANAEROBIC_BENEFIT_0",
    "splitSummaries": [
      {
        "noOfSplits": 8,
        "totalAscent": 0.0,
        "duration": 5.166999816894531,
        "splitType": "RWD_STAND",
        "numClimbSends": 0,
        "maxElevationGain": 0.0,
        "averageElevationGain": 0.0,
        "maxDistance": 4,
        "maxDistanceWithPrecision": 4.019999980926514,
        "distance": 7.059999942779541,
        "averageSpeed": 1.3660000562667847,
        "maxSpeed": 0.0,
        "numFalls": 0,
        "elevationLoss": 0.0
      },
      {
        "noOfSplits": 1,
        "totalAscent": 19.0,
        "duration": 7288.06494140625,
        "splitType": "INTERVAL_ACTIVE",
        "numClimbSends": 0,
        "maxElevationGain": 19.0,
        "averageElevationGain": 19.0,
        "maxDistance": 26008,
        "maxDistanceWithPrecision": 26008.55078125,
        "distance": 26008.55078125,
        "averageSpeed": 3.569000005722046,
        "maxSpeed": 4.301000118255615,
        "numFalls": 0,
        "elevationLoss": 15.0
      },
      {
        "noOfSplits": 5,
        "totalAscent": 19.0,
        "duration": 7276.126953125,
        "splitType": "RWD_RUN",
        "numClimbSends": 0,
        "maxElevationGain": 13.0,
        "averageElevationGain": 5.0,
        "maxDistance": 12208,
        "maxDistanceWithPrecision": 12208.4296875,
        "distance": 25983.0703125,
        "averageSpeed": 3.571000099182129,
        "maxSpeed": 4.301000118255615,
        "numFalls": 0,
        "elevationLoss": 15.0
      },
      {
        "noOfSplits": 11,
        "totalAscent": 0.0,
        "duration": 6.750999927520752,
        "splitType": "RWD_WALK",
        "numClimbSends": 0,
        "maxElevationGain": 0.0,
        "averageElevationGain": 0.0,
        "maxDistance": 7,
        "maxDistanceWithPrecision": 7.690000057220459,
        "distance": 18.43000030517578,
        "averageSpeed": 2.7300000190734863,
        "maxSpeed": 1.847000002861023,
        "numFalls": 0,
        "elevationLoss": 0.0
      }
    ],
    "hasSplits": true,
    "hasIntensityIntervals": false,
    "avgGradeAdjustedSpeed": 3.563999891281128,
    "differenceBodyBattery": -32,
    "hasHeatMap": false,
    "fastestSplit_1000": 268.22900390625,
    "fastestSplit_1609": 435.3689880371094,
    "fastestSplit_5000": 1369.91796875,
    "fastestSplit_10000": 2756.486083984375,
    "fastestSplit_21098": 6212.5341796875,
    "hrTimeInZone_1": 52.468,
    "hrTimeInZone_2": 69.998,
    "hrTimeInZone_3": 4752.769,
    "hrTimeInZone_4": 2386.557,
    "hrTimeInZone_5": 0.0,
    "powerTimeInZone_1": 5212.472,
    "powerTimeInZone_2": 2008.944,
    "powerTimeInZone_3": 24.997,
    "powerTimeInZone_4": 0.0,
    "powerTimeInZone_5": 0.0,
    "endTimeGMT": "2026-06-20 02:40:33",
    "qualifyingDive": false,
    "activityUUID": "33bb533d-0092-4817-92f2-fc038e2d1ff7",
    "autoCalcCalories": false,
    "favorite": false,
    "parent": false,
    "decoDive": false,
    "elevationCorrected": false,
    "atpActivity": false,
    "pr": false,
    "purposeful": false,
    "manualActivity": false,
    "_laps": [
      {
        "startTimeGMT": "2026-06-20T00:24:20.0",
        "startLatitude": 31.115752402693033,
        "startLongitude": 121.75630884245038,
        "distance": 1000.0,
        "duration": 283.382,
        "movingDuration": 283.382,
        "elapsedDuration": 283.382,
        "elevationGain": 0.0,
        "elevationLoss": 0.0,
        "maxElevation": 3.2,
        "minElevation": 0.8,
        "averageSpeed": 3.5290000438690186,
        "averageMovingSpeed": 3.5288057833301623,
        "maxSpeed": 4.021999835968018,
        "calories": 55.0,
        "bmrCalories": 6.0,
        "averageHR": 143.0,
        "maxHR": 156.0,
        "averageRunCadence": 190.234375,
        "maxRunCadence": 198.0,
        "averagePower": 261.0,
        "maxPower": 320.0,
        "minPower": 0.0,
        "normalizedPower": 265.0,
        "totalWork": 17.66101355124797,
        "groundContactTime": 216.3000030517578,
        "strideLength": 110.09000244140626,
        "verticalOscillation": 7.969999694824219,
        "verticalRatio": 7.25,
        "endLatitude": 31.10773293301463,
        "endLongitude": 121.75917964428663,
        "maxVerticalSpeed": 0.39999985694885254,
        "directWorkoutComplianceScore": 37,
        "avgGradeAdjustedSpeed": 3.5160000324249268,
        "lapIndex": 1,
        "wktStepIndex": 0,
        "lengthDTOs": [],
        "wktIndex": 0,
        "connectIQMeasurement": [],
        "intensityType": "ACTIVE",
        "messageIndex": 0
      },
      {
        "startTimeGMT": "2026-06-20T00:29:04.0",
        "startLatitude": 31.107695046812296,
        "startLongitude": 121.75919163040817,
        "distance": 1000.0,
        "duration": 277.875,
        "movingDuration": 277.875,
        "elapsedDuration": 277.875,
        "elevationGain": 0.0,
        "elevationLoss": 1.0,
        "maxElevation": 1.2,
        "minElevation": 0.2,
        "averageSpeed": 3.5989999771118164,
        "averageMovingSpeed": 3.5987404408457047,
        "maxSpeed": 3.8440001010894775,
        "calories": 56.0,
        "bmrCalories": 5.0,
        "averageHR": 152.0,
        "maxHR": 157.0,
        "averageRunCadence": 192.296875,
        "maxRunCadence": 198.0,
        "averagePower": 268.0,
        "maxPower": 290.0,
        "minPower": 242.0,
        "normalizedPower": 268.0,
        "totalWork": 17.8996758965351,
        "groundContactTime": 214.60000610351562,
        "strideLength": 112.10000000000001,
        "verticalOscillation": 8.069999694824219,
        "verticalRatio": 7.199999809265137,
        "endLatitude": 31.101968362927437,
        "endLongitude": 121.7602713033557,
        "maxVerticalSpeed": 0.20000004768371582,
        "directWorkoutComplianceScore": 34,
        "avgGradeAdjustedSpeed": 3.5989999771118164,
        "lapIndex": 2,
        "wktStepIndex": 0,
        "lengthDTOs": [],
        "wktIndex": 0,
        "connectIQMeasurement": [],
        "intensityType": "ACTIVE",
        "messageIndex": 1
      },
      {
        "startTimeGMT": "2026-06-20T00:33:42.0",
        "startLatitude": 31.101972050964832,
        "startLongitude": 121.76023232750595,
        "distance": 1000.0,
        "duration": 285.113,
        "movingDuration": 285.0,
        "elapsedDuration": 824.497,
        "elevationGain": 0.0,
        "elevationLoss": 0.0,
        "maxElevation": 1.2,
        "minElevation": -0.2,
        "averageSpeed": 3.506999969482422,
        "averageMovingSpeed": 3.508771929824561,
        "maxSpeed": 3.8540000915527344,
        "calories": 55.0,
        "bmrCalories": 6.0,
        "averageHR": 142.0,
        "maxHR": 158.0,
        "averageRunCadence": 188.03125,
        "maxRunCadence": 196.0,
        "averagePower": 256.0,
        "maxPower": 298.0,
        "minPower": 0.0,
        "normalizedPower": 255.0,
        "totalWork": 17.422351205960833,
        "groundContactTime": 217.0,
        "strideLength": 110.00999755859375,
        "verticalOscillation": 8.01999969482422,
        "verticalRatio": 7.300000190734863,
        "endLatitude": 31.106096114963293,
        "endLongitude": 121.76183570176363,
        "maxVerticalSpeed": 0.20000004768371582,
        "directWorkoutComplianceScore": 25,
        "avgGradeAdjustedSpeed": 3.4839999675750732,
        "lapIndex": 3,
        "wktStepIndex": 0,
        "lengthDTOs": [],
        "wktIndex": 0,
        "connectIQMeasurement": [],
        "intensityType": "ACTIVE",
        "messageIndex": 2
      },
      {
        "startTimeGMT": "2026-06-20T00:47:27.0",
        "startLatitude": 31.10608471557498,
        "startLongitude": 121.76185489632189,
        "distance": 1000.0,
        "duration": 282.099,
        "movingDuration": 282.0,
        "elapsedDuration": 282.099,
        "elevationGain": 0.0,
        "elevationLoss": 1.0,
        "maxElevation": 0.4,
        "minElevation": -0.6,
        "averageSpeed": 3.5450000762939453,
        "averageMovingSpeed": 3.5460992907801416,
        "maxSpeed": 3.8350000381469727,
        "calories": 58.0,
        "bmrCalories": 6.0,
        "averageHR": 156.0,
        "maxHR": 159.0,
        "averageRunCadence": 192.640625,
        "maxRunCadence": 196.0,
        "averagePower": 270.0,
        "maxPower": 316.0,
        "minPower": 247.0,
        "normalizedPower": 271.0,
        "totalWork": 18.138338241822236,
        "groundContactTime": 215.8000030517578,
        "strideLength": 110.19000244140625,
        "verticalOscillation": 7.990000152587891,
        "verticalRatio": 7.25,
        "endLatitude": 31.103883627802134,
        "endLongitude": 121.75744987092912,
        "maxVerticalSpeed": 0.20000001788139343,
        "directWorkoutComplianceScore": 31,
        "avgGradeAdjustedSpeed": 3.5420000553131104,
        "lapIndex": 4,
        "wktStepIndex": 0,
        "lengthDTOs": [],
        "wktIndex": 0,
        "connectIQMeasurement": [],
        "intensityType": "ACTIVE",
        "messageIndex": 3
      },
      {
        "startTimeGMT": "2026-06-20T00:52:09.0",
        "startLatitude": 31.10391221009195,
        "startLongitude": 121.75743956118822,
        "distance": 1000.0,
        "duration": 281.464,
        "movingDuration": 281.0,
        "elapsedDuration": 281.464,
        "elevationGain": 1.0,
        "elevationLoss": 1.0,
        "maxElevation": 0.6,
        "minElevation": -1.2,
        "averageSpeed": 3.5529999732971196,
        "averageMovingSpeed": 3.5587188612099645,
        "maxSpeed": 3.7790000438690186,
        "calories": 56.0,
        "bmrCalories": 6.0,
        "averageHR": 151.0,
        "maxHR": 158.0,
        "averageRunCadence": 192.25,
        "maxRunCadence": 194.0,
        "averagePower": 259.0,
        "maxPower": 291.0,
        "minPower": 241.0,
        "normalizedPower": 259.0,
        "totalWork": 17.422351205960833,
        "groundContactTime": 216.0,
        "strideLength": 110.45999755859376,
        "verticalOscillation": 8.009999847412109,
        "verticalRatio": 7.25,
        "endLatitude": 31.102985087782145,
        "endLongitude": 121.7623763345182,
        "maxVerticalSpeed": 0.20000004768371582,
        "directWorkoutComplianceScore": 36,
        "avgGradeAdjustedSpeed": 3.5450000762939453,
        "lapIndex": 5,
        "wktStepIndex": 0,
        "lengthDTOs": [],
        "wktIndex": 0,
        "connectIQMeasurement": [],
        "intensityType": "ACTIVE",
        "messageIndex": 4
      },
      {
        "startTimeGMT": "2026-06-20T00:56:50.0",
        "startLatitude": 31.102956756949425,
        "startLongitude": 121.76236116327345,
        "distance": 1000.0,
        "duration": 287.591,
        "movingDuration": 287.591,
        "elapsedDuration": 287.591,
        "elevationGain": 0.0,
        "elevationLoss": 0.0,
        "maxElevation": 0.2,
        "minElevation": -1.0,
        "averageSpeed": 3.4769999980926514,
        "averageMovingSpeed": 3.477160231423011,
        "maxSpeed": 3.7880001068115234,
        "calories": 55.0,
        "bmrCalories": 6.0,
        "averageHR": 143.0,
        "maxHR": 149.0,
        "averageRunCadence": 192.03125,
        "maxRunCadence": 196.0,
        "averagePower": 264.0,
        "maxPower": 295.0,
        "minPower": 224.0,
        "normalizedPower": 265.0,
        "totalWork": 18.138338241822236,
        "groundContactTime": 218.39999389648438,
        "strideLength": 107.95,
        "verticalOscillation": 7.95,
        "verticalRatio": 7.360000133514404,
        "endLatitude": 31.106257969513535,
        "endLongitude": 121.7587580345571,
        "maxVerticalSpeed": 0.20000001788139343,
        "directWorkoutComplianceScore": 42,
        "avgGradeAdjustedSpeed": 3.4719998836517334,
        "lapIndex": 6,
        "wktStepIndex": 0,
        "lengthDTOs": [],
        "wktIndex": 0,
        "connectIQMeasurement": [],
        "intensityType": "ACTIVE",
        "messageIndex": 5
      },
      {
        "startTimeGMT": "2026-06-20T01:01:38.0",
        "startLatitude": 31.106274146586657,
        "startLongitude": 121.7587878741324,
        "distance": 1000.0,
        "duration": 282.267,
        "movingDuration": 282.0,
        "elapsedDuration": 282.267,
        "elevationGain": 1.0,
        "elevationLoss": 1.0,
        "maxElevation": 1.0,
        "minElevation": -0.4,
        "averageSpeed": 3.5429999828338623,
        "averageMovingSpeed": 3.5460992907801416,
        "maxSpeed": 3.7699999809265137,
        "calories": 55.0,
        "bmrCalories": 6.0,
        "averageHR": 147.0,
        "maxHR": 152.0,
        "averageRunCadence": 192.265625,
        "maxRunCadence": 196.0,
        "averagePower": 267.0,
        "maxPower": 294.0,
        "minPower": 239.0,
        "normalizedPower": 267.0,
        "totalWork": 17.8996758965351,
        "groundContactTime": 216.0,
        "strideLength": 110.70999755859376,
        "verticalOscillation": 8.030000305175781,
        "verticalRatio": 7.25,
        "endLatitude": 31.102017983794212,
        "endLongitude": 121.75950771197677,
        "maxVerticalSpeed": 0.20000001788139343,
        "directWorkoutComplianceScore": 43,
        "avgGradeAdjustedSpeed": 3.555000066757202,
        "lapIndex": 7,
        "wktStepIndex": 0,
        "lengthDTOs": [],
        "wktIndex": 0,
        "connectIQMeasurement": [],
        "intensityType": "ACTIVE",
        "messageIndex": 6
      },
      {
        "startTimeGMT": "2026-06-20T01:06:20.0",
        "startLatitude": 31.102024856954813,
        "startLongitude": 121.75946865230799,
        "distance": 1000.0,
        "duration": 282.801,
        "movingDuration": 282.801,
        "elapsedDuration": 282.801,
        "elevationGain": 1.0,
        "elevationLoss": 0.0,
        "maxElevation": 1.2,
        "minElevation": -0.6,
        "averageSpeed": 3.5360000133514404,
        "averageMovingSpeed": 3.5360554528774317,
        "maxSpeed": 3.891000032424927,
        "calories": 53.0,
        "bmrCalories": 6.0,
        "averageHR": 143.0,
        "maxHR": 147.0,
        "averageRunCadence": 190.765625,
        "maxRunCadence": 194.0,
        "averagePower": 263.0,
        "maxPower": 310.0,
        "minPower": 240.0,
        "normalizedPower": 265.0,
        "totalWork": 17.66101355124797,
        "groundContactTime": 218.1999969482422,
        "strideLength": 110.64000244140625,
        "verticalOscillation": 8.130000305175782,
        "verticalRatio": 7.349999904632568,
        "endLatitude": 31.105608539655805,
        "endLongitude": 121.76234222017229,
        "maxVerticalSpeed": 0.20000004768371582,
        "directWorkoutComplianceScore": 47,
        "avgGradeAdjustedSpeed": 3.5329999923706055,
        "lapIndex": 8,
        "wktStepIndex": 0,
        "lengthDTOs": [],
        "wktIndex": 0,
        "connectIQMeasurement": [],
        "intensityType": "ACTIVE",
        "messageIndex": 7
      },
      {
        "startTimeGMT": "2026-06-20T01:11:03.0",
        "startLatitude": 31.105587417259812,
        "startLongitude": 121.76236040890217,
        "distance": 1000.0,
        "duration": 283.564,
        "movingDuration": 283.0,
        "elapsedDuration": 283.564,
        "elevationGain": 1.0,
        "elevationLoss": 1.0,
        "maxElevation": 1.2,
        "minElevation": -0.4,
        "averageSpeed": 3.5269999504089355,
        "averageMovingSpeed": 3.5335689045936394,
        "maxSpeed": 3.7790000438690186,
        "calories": 54.0,
        "bmrCalories": 6.0,
        "averageHR": 145.0,
        "maxHR": 151.0,
        "averageRunCadence": 190.796875,
        "maxRunCadence": 198.0,
        "averagePower": 270.0,
        "maxPower": 306.0,
        "minPower": 230.0,
        "normalizedPower": 271.0,
        "totalWork": 18.138338241822236,
        "groundContactTime": 218.3000030517578,
        "strideLength": 110.50999755859375,
        "verticalOscillation": 8.130000305175782,
        "verticalRatio": 7.349999904632568,
        "endLatitude": 31.104607740417123,
        "endLongitude": 121.75744567997754,
        "maxVerticalSpeed": 0.20000004768371582,
        "directWorkoutComplianceScore": 48,
        "avgGradeAdjustedSpeed": 3.51200008392334,
        "lapIndex": 9,
        "wktStepIndex": 0,
        "lengthDTOs": [],
        "wktIndex": 0,
        "connectIQMeasurement": [],
        "intensityType": "ACTIVE",
        "messageIndex": 8
      },
      {
        "startTimeGMT": "2026-06-20T01:15:46.0",
        "startLatitude": 31.104633808135986,
        "startLongitude": 121.7574476916343,
        "distance": 1000.0,
        "duration": 278.473,
        "movingDuration": 278.473,
        "elapsedDuration": 278.473,
        "elevationGain": 0.0,
        "elevationLoss": 0.0,
        "maxElevation": 1.8,
        "minElevation": 0.6,
        "averageSpeed": 3.5910000801086426,
        "averageMovingSpeed": 3.591012518023282,
        "maxSpeed": 3.927999973297119,
        "calories": 53.0,
        "bmrCalories": 5.0,
        "averageHR": 145.0,
        "maxHR": 150.0,
        "averageRunCadence": 191.296875,
        "maxRunCadence": 194.0,
        "averagePower": 265.0,
        "maxPower": 317.0,
        "minPower": 236.0,
        "normalizedPower": 265.0,
        "totalWork": 17.66101355124797,
        "groundContactTime": 216.39999389648438,
        "strideLength": 111.89000244140625,
        "verticalOscillation": 8.140000152587891,
        "verticalRatio": 7.269999980926514,
        "endLatitude": 31.102433558553457,
        "endLongitude": 121.76177032291889,
        "maxVerticalSpeed": 0.20000004768371582,
        "directWorkoutComplianceScore": 49,
        "avgGradeAdjustedSpeed": 3.5769999027252197,
        "lapIndex": 10,
        "wktStepIndex": 0,
        "lengthDTOs": [],
        "wktIndex": 0,
        "connectIQMeasurement": [],
        "intensityType": "ACTIVE",
        "messageIndex": 9
      },
      {
        "startTimeGMT": "2026-06-20T01:20:25.0",
        "startLatitude": 31.10241117887199,
        "startLongitude": 121.76174509339035,
        "distance": 1000.0,
        "duration": 277.811,
        "movingDuration": 277.811,
        "elapsedDuration": 277.811,
        "elevationGain": 1.0,
        "elevationLoss": 0.0,
        "maxElevation": 2.2,
        "minElevation": 0.8,
        "averageSpeed": 3.5999999046325684,
        "averageMovingSpeed": 3.5995694313860094,
        "maxSpeed": 3.9749999046325684,
        "calories": 56.0,
        "bmrCalories": 5.0,
        "averageHR": 136.0,
        "maxHR": 141.0,
        "averageRunCadence": 192.328125,
        "maxRunCadence": 196.0,
        "averagePower": 273.0,
        "maxPower": 337.0,
        "minPower": 255.0,
        "normalizedPower": 274.0,
        "totalWork": 18.138338241822236,
        "groundContactTime": 214.8000030517578,
        "strideLength": 112.0300048828125,
        "verticalOscillation": 8.069999694824219,
        "verticalRatio": 7.199999809265137,
        "endLatitude": 31.106595508754253,
        "endLongitude": 121.76040415652096,
        "maxVerticalSpeed": 0.20000004768371582,
        "directWorkoutComplianceScore": 48,
        "avgGradeAdjustedSpeed": 3.6050000190734863,
        "lapIndex": 11,
        "wktStepIndex": 0,
        "lengthDTOs": [],
        "wktIndex": 0,
        "connectIQMeasurement": [],
        "intensityType": "ACTIVE",
        "messageIndex": 10
      },
      {
        "startTimeGMT": "2026-06-20T01:25:03.0",
        "startLatitude": 31.10659391619265,
        "startLongitude": 121.76045168191195,
        "distance": 1000.0,
        "duration": 280.021,
        "movingDuration": 280.0,
        "elapsedDuration": 280.021,
        "elevationGain": 1.0,
        "elevationLoss": 0.0,
        "maxElevation": 3.2,
        "minElevation": 1.8,
        "averageSpeed": 3.571000099182129,
        "averageMovingSpeed": 3.571428571428572,
        "maxSpeed": 3.871999979019165,
        "calories": 53.0,
        "bmrCalories": 6.0,
        "averageHR": 144.0,
        "maxHR": 149.0,
        "averageRunCadence": 191.515625,
        "maxRunCadence": 194.0,
        "averagePower": 274.0,
        "maxPower": 322.0,
        "minPower": 242.0,
        "normalizedPower": 274.0,
        "totalWork": 18.37700058710937,
        "groundContactTime": 215.6999969482422,
        "strideLength": 112.48000488281251,
        "verticalOscillation": 8.140000152587891,
        "verticalRatio": 7.239999771118164,
        "endLatitude": 31.102742683142424,
        "endLongitude": 121.75810407847166,
        "maxVerticalSpeed": 0.40000009536743164,
        "directWorkoutComplianceScore": 47,
        "avgGradeAdjustedSpeed": 3.5950000286102295,
        "lapIndex": 12,
        "wktStepIndex": 0,
        "lengthDTOs": [],
        "wktIndex": 0,
        "connectIQMeasurement": [],
        "intensityType": "ACTIVE",
        "messageIndex": 11
      },
      {
        "startTimeGMT": "2026-06-20T01:29:43.0",
        "startLatitude": 31.102770594879985,
        "startLongitude": 121.75808354280889,
        "distance": 1000.0,
        "duration": 290.198,
        "movingDuration": 290.0,
        "elapsedDuration": 290.198,
        "elevationGain": 0.0,
        "elevationLoss": 1.0,
        "maxElevation": 2.6,
        "minElevation": 1.2,
        "averageSpeed": 3.4460000991821294,
        "averageMovingSpeed": 3.4482758620689657,
        "maxSpeed": 3.6110000610351567,
        "calories": 54.0,
        "bmrCalories": 6.0,
        "averageHR": 143.0,
        "maxHR": 148.0,
        "averageRunCadence": 191.3125,
        "maxRunCadence": 195.0,
        "averagePower": 254.0,
        "maxPower": 276.0,
        "minPower": 232.0,
        "normalizedPower": 256.0,
        "totalWork": 17.66101355124797,
        "groundContactTime": 219.3000030517578,
        "strideLength": 108.20999755859376,
        "verticalOscillation": 8.009999847412109,
        "verticalRatio": 7.400000095367432,
        "endLatitude": 31.10513244755566,
        "endLongitude": 121.76262770779431,
        "maxVerticalSpeed": 0.39999997615814215,
        "directWorkoutComplianceScore": 50,
        "avgGradeAdjustedSpeed": 3.4690001010894775,
        "lapIndex": 13,
        "wktStepIndex": 0,
        "lengthDTOs": [],
        "wktIndex": 0,
        "connectIQMeasurement": [],
        "intensityType": "ACTIVE",
        "messageIndex": 12
      },
      {
        "startTimeGMT": "2026-06-20T01:34:33.0",
        "startLatitude": 31.105101518332958,
        "startLongitude": 121.76263927482069,
        "distance": 1000.0,
        "duration": 288.245,
        "movingDuration": 286.0,
        "elapsedDuration": 603.005,
        "elevationGain": 2.0,
        "elevationLoss": 0.0,
        "maxElevation": 2.6,
        "minElevation": -1.6,
        "averageSpeed": 3.4690001010894775,
        "averageMovingSpeed": 3.4965034965034967,
        "maxSpeed": 4.301000118255615,
        "calories": 51.0,
        "bmrCalories": 6.0,
        "averageHR": 134.0,
        "maxHR": 149.0,
        "averageRunCadence": 187.671875,
        "maxRunCadence": 196.0,
        "averagePower": 262.0,
        "maxPower": 335.0,
        "minPower": 0.0,
        "normalizedPower": 263.0,
        "totalWork": 18.138338241822236,
        "groundContactTime": 218.89999389648438,
        "strideLength": 108.25,
        "verticalOscillation": 7.980000305175782,
        "verticalRatio": 7.389999866485596,
        "endLatitude": 31.104268357157707,
        "endLongitude": 121.75744475796819,
        "maxVerticalSpeed": 0.20000004768371582,
        "directWorkoutComplianceScore": 47,
        "avgGradeAdjustedSpeed": 3.424999952316284,
        "lapIndex": 14,
        "wktStepIndex": 0,
        "lengthDTOs": [],
        "wktIndex": 0,
        "connectIQMeasurement": [],
        "intensityType": "ACTIVE",
        "messageIndex": 13
      },
      {
        "startTimeGMT": "2026-06-20T01:44:36.0",
        "startLatitude": 31.10429886728525,
        "startLongitude": 121.75744341686368,
        "distance": 1000.0,
        "duration": 280.576,
        "movingDuration": 280.0,
        "elapsedDuration": 280.576,
        "elevationGain": 0.0,
        "elevationLoss": 1.0,
        "maxElevation": 1.8,
        "minElevation": -0.6,
        "averageSpeed": 3.563999891281128,
        "averageMovingSpeed": 3.571428571428572,
        "maxSpeed": 3.9100000858306885,
        "calories": 54.0,
        "bmrCalories": 6.0,
        "averageHR": 140.0,
        "maxHR": 144.0,
        "averageRunCadence": 192.578125,
        "maxRunCadence": 196.0,
        "averagePower": 260.0,
        "maxPower": 310.0,
        "minPower": 235.0,
        "normalizedPower": 261.0,
        "totalWork": 17.422351205960833,
        "groundContactTime": 215.39999389648438,
        "strideLength": 110.7699951171875,
        "verticalOscillation": 8.009999847412109,
        "verticalRatio": 7.230000019073486,
        "endLatitude": 31.102655678987503,
        "endLongitude": 121.76208296790719,
        "maxVerticalSpeed": 0.20000004768371582,
        "directWorkoutComplianceScore": 47,
        "avgGradeAdjustedSpeed": 3.5529999732971196,
        "lapIndex": 15,
        "wktStepIndex": 0,
        "lengthDTOs": [],
        "wktIndex": 0,
        "connectIQMeasurement": [],
        "intensityType": "ACTIVE",
        "messageIndex": 14
      },
      {
        "startTimeGMT": "2026-06-20T01:49:16.0",
        "startLatitude": 31.10262625850737,
        "startLongitude": 121.7620547208935,
        "distance": 1000.0,
        "duration": 274.067,
        "movingDuration": 274.067,
        "elapsedDuration": 274.067,
        "elevationGain": 2.0,
        "elevationLoss": 0.0,
        "maxElevation": 2.2,
        "minElevation": -0.2,
        "averageSpeed": 3.6489999294281006,
        "averageMovingSpeed": 3.648743010927856,
        "maxSpeed": 3.7980000972747807,
        "calories": 51.0,
        "bmrCalories": 5.0,
        "averageHR": 144.0,
        "maxHR": 150.0,
        "averageRunCadence": 192.859375,
        "maxRunCadence": 196.0,
        "averagePower": 275.0,
        "maxPower": 304.0,
        "minPower": 256.0,
        "normalizedPower": 276.0,
        "totalWork": 18.138338241822236,
        "groundContactTime": 213.39999389648438,
        "strideLength": 112.66999511718751,
        "verticalOscillation": 8.05999984741211,
        "verticalRatio": 7.150000095367432,
        "endLatitude": 31.10659341327846,
        "endLongitude": 121.76003853790462,
        "maxVerticalSpeed": 0.20000004768371582,
        "directWorkoutComplianceScore": 45,
        "avgGradeAdjustedSpeed": 3.634999990463257,
        "lapIndex": 16,
        "wktStepIndex": 0,
        "lengthDTOs": [],
        "wktIndex": 0,
        "connectIQMeasurement": [],
        "intensityType": "ACTIVE",
        "messageIndex": 15
      },
      {
        "startTimeGMT": "2026-06-20T01:53:51.0",
        "startLatitude": 31.10659919679165,
        "startLongitude": 121.76007265225053,
        "distance": 1000.0,
        "duration": 274.789,
        "movingDuration": 274.0,
        "elapsedDuration": 274.789,
        "elevationGain": 0.0,
        "elevationLoss": 0.0,
        "maxElevation": 2.2,
        "minElevation": 1.4,
        "averageSpeed": 3.638999938964844,
        "averageMovingSpeed": 3.6496350364963503,
        "maxSpeed": 3.927999973297119,
        "calories": 51.0,
        "bmrCalories": 5.0,
        "averageHR": 146.0,
        "maxHR": 150.0,
        "averageRunCadence": 192.796875,
        "maxRunCadence": 196.0,
        "averagePower": 275.0,
        "maxPower": 316.0,
        "minPower": 242.0,
        "normalizedPower": 274.0,
        "totalWork": 17.8996758965351,
        "groundContactTime": 213.3000030517578,
        "strideLength": 112.8300048828125,
        "verticalOscillation": 8.05999984741211,
        "verticalRatio": 7.139999866485596,
        "endLatitude": 31.102536069229245,
        "endLongitude": 121.75832678563893,
        "maxVerticalSpeed": 0.20000004768371582,
        "directWorkoutComplianceScore": 44,
        "avgGradeAdjustedSpeed": 3.634999990463257,
        "lapIndex": 17,
        "wktStepIndex": 0,
        "lengthDTOs": [],
        "wktIndex": 0,
        "connectIQMeasurement": [],
        "intensityType": "ACTIVE",
        "messageIndex": 16
      },
      {
        "startTimeGMT": "2026-06-20T01:58:25.0",
        "startLatitude": 31.102554090321064,
        "startLongitude": 121.75828856416047,
        "distance": 1000.0,
        "duration": 271.483,
        "movingDuration": 271.483,
        "elapsedDuration": 271.483,
        "elevationGain": 0.0,
        "elevationLoss": 0.0,
        "maxElevation": 2.6,
        "minElevation": 1.4,
        "averageSpeed": 3.6830000877380376,
        "averageMovingSpeed": 3.683471870080278,
        "maxSpeed": 3.947000026702881,
        "calories": 52.0,
        "bmrCalories": 5.0,
        "averageHR": 147.0,
        "maxHR": 152.0,
        "averageRunCadence": 193.03125,
        "maxRunCadence": 196.0,
        "averagePower": 268.0,
        "maxPower": 310.0,
        "minPower": 255.0,
        "normalizedPower": 269.0,
        "totalWork": 17.422351205960833,
        "groundContactTime": 212.3000030517578,
        "strideLength": 113.69000244140625,
        "verticalOscillation": 8.069999694824219,
        "verticalRatio": 7.099999904632568,
        "endLatitude": 31.104450495913625,
        "endLongitude": 121.76280347630382,
        "maxVerticalSpeed": 0.20000004768371582,
        "directWorkoutComplianceScore": 43,
        "avgGradeAdjustedSpeed": 3.6730000972747803,
        "lapIndex": 18,
        "wktStepIndex": 0,
        "lengthDTOs": [],
        "wktIndex": 0,
        "connectIQMeasurement": [],
        "intensityType": "ACTIVE",
        "messageIndex": 17
      },
      {
        "startTimeGMT": "2026-06-20T02:02:57.0",
        "startLatitude": 31.10441856086254,
        "startLongitude": 121.76281102001667,
        "distance": 1000.0,
        "duration": 273.839,
        "movingDuration": 273.839,
        "elapsedDuration": 273.839,
        "elevationGain": 3.0,
        "elevationLoss": 0.0,
        "maxElevation": 6.2,
        "minElevation": 1.8,
        "averageSpeed": 3.6519999504089355,
        "averageMovingSpeed": 3.651780934155162,
        "maxSpeed": 3.937999963760376,
        "calories": 53.0,
        "bmrCalories": 5.0,
        "averageHR": 148.0,
        "maxHR": 152.0,
        "averageRunCadence": 193.84375,
        "maxRunCadence": 198.0,
        "averagePower": 286.0,
        "maxPower": 314.0,
        "minPower": 258.0,
        "normalizedPower": 287.0,
        "totalWork": 18.615662932396507,
        "groundContactTime": 211.60000610351562,
        "strideLength": 113.40999755859376,
        "verticalOscillation": 8.01999969482422,
        "verticalRatio": 7.070000171661377,
        "endLatitude": 31.10572462901473,
        "endLongitude": 121.75800944678485,
        "maxVerticalSpeed": 0.20000028610229495,
        "directWorkoutComplianceScore": 42,
        "avgGradeAdjustedSpeed": 3.700000047683716,
        "lapIndex": 19,
        "wktStepIndex": 0,
        "lengthDTOs": [],
        "wktIndex": 0,
        "connectIQMeasurement": [],
        "intensityType": "ACTIVE",
        "messageIndex": 18
      },
      {
        "startTimeGMT": "2026-06-20T02:07:31.0",
        "startLatitude": 31.105752624571323,
        "startLongitude": 121.75803576596081,
        "distance": 1000.0,
        "duration": 279.183,
        "movingDuration": 279.0,
        "elapsedDuration": 279.183,
        "elevationGain": 0.0,
        "elevationLoss": 0.0,
        "maxElevation": 6.4,
        "minElevation": 4.8,
        "averageSpeed": 3.582000017166138,
        "averageMovingSpeed": 3.584229390681004,
        "maxSpeed": 3.86299991607666,
        "calories": 51.0,
        "bmrCalories": 5.0,
        "averageHR": 146.0,
        "maxHR": 151.0,
        "averageRunCadence": 193.828125,
        "maxRunCadence": 198.0,
        "averagePower": 266.0,
        "maxPower": 303.0,
        "minPower": 247.0,
        "normalizedPower": 265.0,
        "totalWork": 17.66101355124797,
        "groundContactTime": 214.10000610351562,
        "strideLength": 110.3300048828125,
        "verticalOscillation": 7.919999694824219,
        "verticalRatio": 7.179999828338623,
        "endLatitude": 31.101954197511077,
        "endLongitude": 121.7605089303106,
        "maxVerticalSpeed": 0.20000028610229495,
        "directWorkoutComplianceScore": 43,
        "avgGradeAdjustedSpeed": 3.563999891281128,
        "lapIndex": 20,
        "wktStepIndex": 0,
        "lengthDTOs": [],
        "wktIndex": 0,
        "connectIQMeasurement": [],
        "intensityType": "ACTIVE",
        "messageIndex": 19
      },
      {
        "startTimeGMT": "2026-06-20T02:12:10.0",
        "startLatitude": 31.101947659626603,
        "startLongitude": 121.76046869717538,
        "distance": 1000.0,
        "duration": 277.884,
        "movingDuration": 277.884,
        "elapsedDuration": 277.884,
        "elevationGain": 1.0,
        "elevationLoss": 1.0,
        "maxElevation": 7.0,
        "minElevation": 5.0,
        "averageSpeed": 3.5989999771118164,
        "averageMovingSpeed": 3.5986238514478233,
        "maxSpeed": 3.7320001125335693,
        "calories": 52.0,
        "bmrCalories": 5.0,
        "averageHR": 146.0,
        "maxHR": 151.0,
        "averageRunCadence": 193.9375,
        "maxRunCadence": 198.0,
        "averagePower": 265.0,
        "maxPower": 293.0,
        "minPower": 251.0,
        "normalizedPower": 266.0,
        "totalWork": 17.66101355124797,
        "groundContactTime": 213.60000610351562,
        "strideLength": 110.7,
        "verticalOscillation": 7.930000305175781,
        "verticalRatio": 7.159999847412109,
        "endLatitude": 31.106167947873473,
        "endLongitude": 121.76169471815228,
        "maxVerticalSpeed": 0.20000028610229495,
        "directWorkoutComplianceScore": 43,
        "avgGradeAdjustedSpeed": 3.5789999961853027,
        "lapIndex": 21,
        "wktStepIndex": 0,
        "lengthDTOs": [],
        "wktIndex": 0,
        "connectIQMeasurement": [],
        "intensityType": "ACTIVE",
        "messageIndex": 20
      },
      {
        "startTimeGMT": "2026-06-20T02:16:48.0",
        "startLatitude": 31.106142047792673,
        "startLongitude": 121.76172690466046,
        "distance": 1000.0,
        "duration": 278.76,
        "movingDuration": 278.76,
        "elapsedDuration": 278.76,
        "elevationGain": 0.0,
        "elevationLoss": 2.0,
        "maxElevation": 5.2,
        "minElevation": 3.2,
        "averageSpeed": 3.5869998931884766,
        "averageMovingSpeed": 3.5873151275922863,
        "maxSpeed": 3.750999927520752,
        "calories": 52.0,
        "bmrCalories": 5.0,
        "averageHR": 147.0,
        "maxHR": 150.0,
        "averageRunCadence": 193.953125,
        "maxRunCadence": 198.0,
        "averagePower": 271.0,
        "maxPower": 291.0,
        "minPower": 251.0,
        "normalizedPower": 271.0,
        "totalWork": 18.138338241822236,
        "groundContactTime": 213.5,
        "strideLength": 110.8199951171875,
        "verticalOscillation": 7.930000305175781,
        "verticalRatio": 7.150000095367432,
        "endLatitude": 31.103815902024508,
        "endLongitude": 121.75744626671076,
        "maxVerticalSpeed": 0.20000028610229495,
        "directWorkoutComplianceScore": 43,
        "avgGradeAdjustedSpeed": 3.5799999237060547,
        "lapIndex": 22,
        "wktStepIndex": 0,
        "lengthDTOs": [],
        "wktIndex": 0,
        "connectIQMeasurement": [],
        "intensityType": "ACTIVE",
        "messageIndex": 21
      },
      {
        "startTimeGMT": "2026-06-20T02:21:27.0",
        "startLatitude": 31.10385655425489,
        "startLongitude": 121.75744626671076,
        "distance": 1000.0,
        "duration": 275.221,
        "movingDuration": 275.0,
        "elapsedDuration": 275.221,
        "elevationGain": 1.0,
        "elevationLoss": 1.0,
        "maxElevation": 4.6,
        "minElevation": 3.0,
        "averageSpeed": 3.632999897003174,
        "averageMovingSpeed": 3.6363636363636362,
        "maxSpeed": 3.8350000381469727,
        "calories": 53.0,
        "bmrCalories": 5.0,
        "averageHR": 150.0,
        "maxHR": 152.0,
        "averageRunCadence": 194.25,
        "maxRunCadence": 198.0,
        "averagePower": 265.0,
        "maxPower": 294.0,
        "minPower": 237.0,
        "normalizedPower": 265.0,
        "totalWork": 17.422351205960833,
        "groundContactTime": 211.89999389648438,
        "strideLength": 112.30000000000001,
        "verticalOscillation": 7.95999984741211,
        "verticalRatio": 7.090000152587891,
        "endLatitude": 31.103047197684646,
        "endLongitude": 121.7623813636601,
        "maxVerticalSpeed": 0.20000028610229495,
        "directWorkoutComplianceScore": 41,
        "avgGradeAdjustedSpeed": 3.6419999599456787,
        "lapIndex": 23,
        "wktStepIndex": 0,
        "lengthDTOs": [],
        "wktIndex": 0,
        "connectIQMeasurement": [],
        "intensityType": "ACTIVE",
        "messageIndex": 22
      },
      {
        "startTimeGMT": "2026-06-20T02:26:02.0",
        "startLatitude": 31.10301752574742,
        "startLongitude": 121.76236644387245,
        "distance": 1000.0,
        "duration": 273.505,
        "movingDuration": 273.0,
        "elapsedDuration": 273.505,
        "elevationGain": 1.0,
        "elevationLoss": 0.0,
        "maxElevation": 5.4,
        "minElevation": 3.2,
        "averageSpeed": 3.6559998989105225,
        "averageMovingSpeed": 3.6630036630036633,
        "maxSpeed": 3.891000032424927,
        "calories": 54.0,
        "bmrCalories": 5.0,
        "averageHR": 152.0,
        "maxHR": 155.0,
        "averageRunCadence": 194.40625,
        "maxRunCadence": 198.0,
        "averagePower": 278.0,
        "maxPower": 326.0,
        "minPower": 243.0,
        "normalizedPower": 280.0,
        "totalWork": 18.138338241822236,
        "groundContactTime": 211.8000030517578,
        "strideLength": 112.0699951171875,
        "verticalOscillation": 7.940000152587891,
        "verticalRatio": 7.079999923706055,
        "endLatitude": 31.106486124917865,
        "endLongitude": 121.75945146940649,
        "maxVerticalSpeed": 0.39999985694885254,
        "directWorkoutComplianceScore": 40,
        "avgGradeAdjustedSpeed": 3.654000043869019,
        "lapIndex": 24,
        "wktStepIndex": 0,
        "lengthDTOs": [],
        "wktIndex": 0,
        "connectIQMeasurement": [],
        "intensityType": "ACTIVE",
        "messageIndex": 23
      },
      {
        "startTimeGMT": "2026-06-20T02:30:35.0",
        "startLatitude": 31.106486711651087,
        "startLongitude": 121.75949145108461,
        "distance": 1000.0,
        "duration": 282.932,
        "movingDuration": 282.932,
        "elapsedDuration": 282.932,
        "elevationGain": 0.0,
        "elevationLoss": 1.0,
        "maxElevation": 4.8,
        "minElevation": 2.4,
        "averageSpeed": 3.5339999198913574,
        "averageMovingSpeed": 3.5344180786865356,
        "maxSpeed": 3.8350000381469727,
        "calories": 55.0,
        "bmrCalories": 6.0,
        "averageHR": 152.0,
        "maxHR": 159.0,
        "averageRunCadence": 193.109375,
        "maxRunCadence": 197.0,
        "averagePower": 263.0,
        "maxPower": 303.0,
        "minPower": 238.0,
        "normalizedPower": 263.0,
        "totalWork": 17.66101355124797,
        "groundContactTime": 215.5,
        "strideLength": 109.94000244140625,
        "verticalOscillation": 7.95999984741211,
        "verticalRatio": 7.230000019073486,
        "endLatitude": 31.108444472774863,
        "endLongitude": 121.75890262238681,
        "maxVerticalSpeed": 0.20000028610229495,
        "directWorkoutComplianceScore": 41,
        "avgGradeAdjustedSpeed": 3.5299999713897705,
        "lapIndex": 25,
        "wktStepIndex": 0,
        "lengthDTOs": [],
        "wktIndex": 0,
        "connectIQMeasurement": [],
        "intensityType": "ACTIVE",
        "messageIndex": 24
      },
      {
        "startTimeGMT": "2026-06-20T02:35:18.0",
        "startLatitude": 31.108475318178535,
        "startLongitude": 121.75889331847429,
        "distance": 999.99,
        "duration": 283.042,
        "movingDuration": 282.0,
        "elapsedDuration": 314.675,
        "elevationGain": 1.0,
        "elevationLoss": 1.0,
        "maxElevation": 3.8,
        "minElevation": 1.6,
        "averageSpeed": 3.5329999923706055,
        "averageMovingSpeed": 3.5460637951573584,
        "maxSpeed": 4.021999835968018,
        "calories": 53.0,
        "bmrCalories": 6.0,
        "averageHR": 150.0,
        "maxHR": 156.0,
        "averageRunCadence": 189.9375,
        "maxRunCadence": 199.0,
        "averagePower": 261.0,
        "maxPower": 319.0,
        "minPower": 0.0,
        "normalizedPower": 258.0,
        "totalWork": 17.66101355124797,
        "groundContactTime": 215.0,
        "strideLength": 110.1300048828125,
        "verticalOscillation": 7.95,
        "verticalRatio": 7.21999979019165,
        "endLatitude": 31.115336325019598,
        "endLongitude": 121.75569402985275,
        "maxVerticalSpeed": 0.20000004768371582,
        "directWorkoutComplianceScore": 41,
        "avgGradeAdjustedSpeed": 3.530999898910523,
        "lapIndex": 26,
        "wktStepIndex": 0,
        "lengthDTOs": [],
        "wktIndex": 0,
        "connectIQMeasurement": [],
        "intensityType": "ACTIVE",
        "messageIndex": 25
      },
      {
        "startTimeGMT": "2026-06-20T02:40:33.0",
        "startLatitude": 31.115309335291386,
        "startLongitude": 121.75570593215525,
        "distance": 8.56,
        "duration": 1.88,
        "movingDuration": 1.0,
        "elapsedDuration": 1.88,
        "elevationGain": 0.0,
        "elevationLoss": 0.0,
        "maxElevation": 3.8,
        "minElevation": 3.8,
        "averageSpeed": 4.552000045776367,
        "averageMovingSpeed": 8.5600004196167,
        "maxSpeed": 3.3499999046325684,
        "calories": 0.0,
        "bmrCalories": 0.0,
        "averageHR": 152.0,
        "maxHR": 152.0,
        "averageRunCadence": 192.0,
        "maxRunCadence": 192.0,
        "averagePower": 248.0,
        "maxPower": 249.0,
        "minPower": 247.0,
        "normalizedPower": 260.0,
        "totalWork": 0.0,
        "groundContactTime": 222.0,
        "strideLength": 104.60000000000001,
        "verticalOscillation": 7.8500000000000005,
        "verticalRatio": 7.5,
        "endLatitude": 31.11528318375349,
        "endLongitude": 121.75571481697261,
        "maxVerticalSpeed": 0.0,
        "avgGradeAdjustedSpeed": 3.3959999084472656,
        "lapIndex": 27,
        "lengthDTOs": [],
        "connectIQMeasurement": [],
        "intensityType": "ACTIVE",
        "messageIndex": 26
      }
    ]
  }
]